[
    {
        "fields": {
            "user_attendance": 2115,
            "status": 1,
            "created": "2014-12-01",
            "polymorphic_ctype": ["dpnk", "payment"]
        },
        "model": "dpnk.transaction",
        "pk": 5
    },
    {
        "fields": {
            "amount": 150,
            "pay_type": "fc",
            "trans_id": "2055-1",
            "session_id": "2075-1J1455206453",
            "transaction_ptr": 5
        },
        "model": "dpnk.payment",
        "pk": 5
    },
    {
        "fields": {
            "user_attendance": 1115,
            "polymorphic_ctype": ["dpnk", "payment"]
        },
        "model": "dpnk.transaction",
        "pk": 3
    },
    {
        "fields": {
            "amount": 150,
            "trans_id": "2075-1",
            "session_id": "2075-1J1455206433",
            "transaction_ptr": 3
        },
        "model": "dpnk.payment",
        "pk": 3
    },
    {
        "fields": {
            "user_attendance": 1115,
            "status": 99,
            "realized": "2010-11-01",
            "polymorphic_ctype": ["dpnk", "payment"]
        },
        "model": "dpnk.transaction",
        "pk": 4
    },
    {
        "fields": {
            "amount": 145,
            "pay_type": "fc",
            "trans_id": "2075-2",
            "session_id": "2075-1J1455206444",
            "transaction_ptr": 4
        },
        "model": "dpnk.payment",
        "pk": 4
    }
]
